LICENSE
README.md
setup.cfg
setup.py
Kinop.egg-info/PKG-INFO
Kinop.egg-info/SOURCES.txt
Kinop.egg-info/dependency_links.txt
Kinop.egg-info/top_level.txt
mikomusic/__init__.py
mikomusic/_classes.py
mikomusic/_emojis.py
mikomusic/_version.py
mikomusic/checks.py
mikomusic/errors.py
mikomusic/events.py
mikomusic/music.py
mikomusic/paginator.py
mikomusic/player.py
mikomusic/volumembed.py